{
    "project": "Homework Assignment",
    "title": "Derivative WorkSheet",
    "double_column": false,
    "date": "11/11/2024",
    "author": "Signore",
    "description": "This is a homework assignment for the Calculus I class at the ETITC.",
    "students": ["Santiago", "Jose"],
    "questions": [
        {
            "type": "generic",
            "statement": ["QSBjb250aW51YWNpb24gbGEgZGVmaW5pY2lvbiBkZSBsYSBpbnRlZ3JhbCBwb3IgcGFydGVz", "XFtcaW50IHVkdj11di1caW50IHZkdVxd", "QmFzYWRvIGVuIGVzbywgcmVzdWVsdmEgbGFzIHNpZ3VpZW50ZXMgb3BlcmFjaW9uZXM="],
            "choices": [["SW50ZWdyYWwgZGVmaW5pZGFcXA==","XChcaW50IHhjb3MoeClkeFwp="],["XChcaW50IHhjb3MoeClkeFwp="],["XChcaW50IHhjb3MoeClkeFwp="],["XChcaW50IHhjb3MoeClkeFwp="]],
            "solution": ["XGludCB4Y29zKHgpZHg="]
        },
        {
            "type": "generic",
            "statement": ["QSBjb250aW51YWNpb24gbGEgZGVmaW5pY2lvbiBkZSBsYSBpbnRlZ3JhbCBwb3IgcGFydGVz","XFtcaW50IHVkdj11di1caW50IHZkdVxd", "QmFzYWRvIGVuIGVzbywgcmVzdWVsdmEgbGFzIHNpZ3VpZW50ZXMgb3BlcmFjaW9uZXM="],
            "choices": [["XChcaW50IHhjb3MoeClkeFwp="],["XChcaW50IHhjb3MoeClkeFwp="],["XChcaW50IHhjb3MoeClkeFwp="],["XChcaW50IHhjb3MoeClkeFwp="]],
            "solution": ["XGludCB4Y29zKHgpZHg="]
        }
    ]
}